Workbook

Sheet Project_Overview
A1: Revenue Forecast & Scenario Analysis Model
A2: Jordan Brown
A3: 46081
A5: This project models 12 months of projected revenue and profitability using dynamic growth assumptions. The model incorporates scenario-based forecasting (Conservative, Base, Optimistic) and automatically updates financial projections and KPIs.
A7: Tools & Skills:
A8: • Financial forecasting
A9: • Scenario analysis
A10: • Excel financial modeling
A11: • XLOOKUP
A12: • Dashboard development

Sheet Assumptions
A1: Revenue Forecast Assumptions
D2: Scenario Inputs
A3: Starting Revenue | B3: 780000 | D3: Scenario | E3: Monthly Growth Rate
A4: Monthly Growth Rate | B4: =_xlfn.XLOOKUP($B$8,$D$4:$D$6,$E$4:$E$6) -> 0.05 | D4: Conservative | E4: 0.02
A5: COGS % of Revenue | B5: 0.4 | D5: Base | E5: 0.05
A6: Operating Expense Growth Rate | B6: 0.02 | D6: Optimistic | E6: 0.08
A8: Scenario Selected | B8: Base

Sheet Forecast_Model
A1: Month | B1: Projected Revenue | C1: Projected COGS | D1: Projected Operating Expense | E1: Projected Net Income
A2: Jan | B2: =Assumptions!B3 -> 780000 | C2: =B2*Assumptions!$B$5 -> 312000 | D2: 165000 | E2: =B2-(C2+D2) -> 303000
A3: Feb | B3: =B2*(1+Assumptions!$B$4) -> 819000 | C3: =B3*Assumptions!$B$5 -> 327600 | D3: =D2*(1+Assumptions!$B$6) -> 168300 | E3: =B3-(C3+D3) -> 323100
A4: Mar | B4: =B3*(1+Assumptions!$B$4) -> 859950 | C4: =B4*Assumptions!$B$5 -> 343980 | D4: =D3*(1+Assumptions!$B$6) -> 171666 | E4: =B4-(C4+D4) -> 344304
A5: Apr | B5: =B4*(1+Assumptions!$B$4) -> 902947.5 | C5: =B5*Assumptions!$B$5 -> 361179 | D5: =D4*(1+Assumptions!$B$6) -> 175099.32 | E5: =B5-(C5+D5) -> 366669.18
A6: May | B6: =B5*(1+Assumptions!$B$4) -> 948094.88 | C6: =B6*Assumptions!$B$5 -> 379237.95 | D6: =D5*(1+Assumptions!$B$6) -> 178601.31 | E6: =B6-(C6+D6) -> 390255.62
A7: Jun | B7: =B6*(1+Assumptions!$B$4) -> 995499.62 | C7: =B7*Assumptions!$B$5 -> 398199.85 | D7: =D6*(1+Assumptions!$B$6) -> 182173.33 | E7: =B7-(C7+D7) -> 415126.44
A8: Jul | B8: =B7*(1+Assumptions!$B$4) -> 1045274.6 | C8: =B8*Assumptions!$B$5 -> 418109.84 | D8: =D7*(1+Assumptions!$B$6) -> 185816.8 | E8: =B8-(C8+D8) -> 441347.96
A9: Aug | B9: =B8*(1+Assumptions!$B$4) -> 1097538.3 | C9: =B9*Assumptions!$B$5 -> 439015.33 | D9: =D8*(1+Assumptions!$B$6) -> 189533.14 | E9: =B9-(C9+D9) -> 468989.86
A10: Sep | B10: =B9*(1+Assumptions!$B$4) -> 1152415.2 | C10: =B10*Assumptions!$B$5 -> 460966.1 | D10: =D9*(1+Assumptions!$B$6) -> 193323.8 | E10: =B10-(C10+D10) -> 498125.35
A11: Oct | B11: =B10*(1+Assumptions!$B$4) -> 1210036 | C11: =B11*Assumptions!$B$5 -> 484014.4 | D11: =D10*(1+Assumptions!$B$6) -> 197190.27 | E11: =B11-(C11+D11) -> 528831.33
A12: Nov | B12: =B11*(1+Assumptions!$B$4) -> 1270537.8 | C12: =B12*Assumptions!$B$5 -> 508215.12 | D12: =D11*(1+Assumptions!$B$6) -> 201134.08 | E12: =B12-(C12+D12) -> 561188.61
A13: Dec | B13: =B12*(1+Assumptions!$B$4) -> 1334064.7 | C13: =B13*Assumptions!$B$5 -> 533625.88 | D13: =D12*(1+Assumptions!$B$6) -> 205156.76 | E13: =B13-(C13+D13) -> 595282.06

Sheet Dashboard
B2: Scenario | D2: Total Projected Revenue | F2: Total Projected Net Income | H2: Projected Profit Margin
B3: =Assumptions!B8 -> Base | D3: =SUM(Forecast_Model!B2:B13) -> 12415359 | F3: =SUM(Forecast_Model!E2:E13) -> 5236220.4 | H3: =F3/D3 -> 0.42175345
D38: Executive Summary
D39: • Revenue projections adjust dynamically based on selected growth scenario.
D40: • Under the Base case (5% growth), total projected revenue reaches $12,415,359.
D41: • Net income scales proportionally due to fixed COGS % structure.
D42: • The model highlights the impact of growth assumptions on profitability and long-term financial outcomes.
